pgvector_storage/.gitignore
pgvector_storage/__init__.py
pgvector_storage/document.py
pgvector_storage/pgvector_storage_dao.py
pgvector_storage-0.1.4.dist-info/METADATA
pgvector_storage-0.1.4.dist-info/WHEEL
pgvector_storage-0.1.4.dist-info/RECORD
